tvallogging/__init__.py
tvallogging/api.py
tvallogging/chat_objects.py
tvallogging/classes/__init__.py
tvallogging/classes/http_client.py
tvallogging/classes/project.py
tvallogging/classes/run.py
tvallogging/logging_util.py
tvallogging/services/__init__.py
tvallogging/services/benchmark_service.py
tvallogging/services/project_service.py
tvallogging/services/run_service.py
tvallogging-1.0.0.dist-info/LICENSE
tvallogging-1.0.0.dist-info/METADATA
tvallogging-1.0.0.dist-info/WHEEL
tvallogging-1.0.0.dist-info/RECORD
