Metadata-Version: 2.1
Name: tvallogging
Version: 1.0.0
Summary: Logging for Tonic Validate
Author: Joe Ferrara
Author-email: joeferrara@tonic.ai
Requires-Python: >=3.8.1,<4.0.0
Classifier: Programming Language :: Python :: 3
Classifier: Programming Language :: Python :: 3.9
Classifier: Programming Language :: Python :: 3.10
Classifier: Programming Language :: Python :: 3.11
Classifier: Programming Language :: Python :: 3.12
Requires-Dist: tvalmetrics (>=1.0.0,<2.0.0)
